itkwasm_downsample_cucim/__init__.py
itkwasm_downsample_cucim/_discrete_gaussian.py
itkwasm_downsample_cucim/_version.py
itkwasm_downsample_cucim/downsample.py
itkwasm_downsample_cucim/downsample_bin_shrink.py
itkwasm_downsample_cucim-0.2.0.dist-info/METADATA
itkwasm_downsample_cucim-0.2.0.dist-info/WHEEL
itkwasm_downsample_cucim-0.2.0.dist-info/entry_points.txt
itkwasm_downsample_cucim-0.2.0.dist-info/RECORD
