Metadata-Version: 2.1
Name: itkwasm-downsample-cucim
Version: 0.2.0
Summary: Pipelines for downsampling images. cuCIM implementation.
Project-URL: Home, https://github.com/InsightSoftwareConsortium/itk-wasm
Project-URL: Source, https://github.com/InsightSoftwareConsortium/itk-wasm
License-Expression: Apache-2.0
Keywords: itkwasm,wasi,webassembly
Classifier: Development Status :: 3 - Alpha
Classifier: Environment :: WebAssembly
Classifier: Environment :: WebAssembly :: Emscripten
Classifier: Environment :: WebAssembly :: WASI
Classifier: Intended Audience :: Developers
Classifier: Intended Audience :: Science/Research
Classifier: License :: OSI Approved :: Apache Software License
Classifier: Programming Language :: C++
Classifier: Programming Language :: Python
Classifier: Programming Language :: Python :: 3
Classifier: Programming Language :: Python :: 3.8
Classifier: Programming Language :: Python :: 3.9
Classifier: Programming Language :: Python :: 3.10
Classifier: Programming Language :: Python :: 3.11
Classifier: Programming Language :: Python :: 3.12
Requires-Python: >=3.8
Requires-Dist: itkwasm-downsample-wasi
Requires-Dist: itkwasm>=1.0.b168
